pycontbin/__init__.py
pycontbin/pycontbin.py
pycontbin-0.2.0.dist-info/METADATA
pycontbin-0.2.0.dist-info/WHEEL
pycontbin-0.2.0.dist-info/top_level.txt
pycontbin-0.2.0.dist-info/RECORD
