Metadata-Version: 2.1
Name: pycontbin
Version: 0.2.0
Summary: A Python implementation of the ContBin algorithm
Home-page: https://github.com/jpbreuer/contbin_python
Author: Jean-Paul Breuer
Author-email: jeanpaul.breuer@gmail.com
License: BSD 2-clause
Classifier: Programming Language :: Python :: 3
Classifier: License :: OSI Approved :: MIT License
Classifier: Intended Audience :: Science/Research
Classifier: Operating System :: POSIX :: Linux
Requires-Python: >=3.6
Requires-Dist: numpy
Requires-Dist: astropy
Requires-Dist: pyds9
